decoding/__init__.py
decoding/estimators.py
decoding/experimental.py
decoding/generators.py
decoding/metrics.py
decoding/models.py
decoding/pmf.py
decoding/samplers.py
decoding/scorers.py
decoding/types.py
decoding/utils.py
decoding-0.1.4.dist-info/LICENSE
decoding-0.1.4.dist-info/METADATA
decoding-0.1.4.dist-info/WHEEL
decoding-0.1.4.dist-info/top_level.txt
decoding-0.1.4.dist-info/RECORD
