Metadata-Version: 2.1
Name: decoding
Version: 0.1.4
Summary: Composable inference algorithms with LLMs and programmable logic
License: Apache 2.0
Requires-Python: >=3.11
License-File: LICENSE
Requires-Dist: jax==0.4.35
Requires-Dist: jaxtyping==0.2.36
Requires-Dist: vllm==0.6.3.post1
Provides-Extra: dev
Requires-Dist: pdoc==15.0.0; extra == "dev"
Requires-Dist: pre-commit==4.0.1; extra == "dev"
Requires-Dist: pyright==1.1.389; extra == "dev"
Requires-Dist: pytest==8.3.3; extra == "dev"
Requires-Dist: pytest-cov==6.0.0; extra == "dev"
Requires-Dist: pytest-html==4.1.1; extra == "dev"
Requires-Dist: ruff==0.8.0; extra == "dev"
